{
  "title": "YugabyteDB SQL shell",
  "description": "YugabyteDB SQL shell",
  "difficulty": "Beginner",
  "time": "1 minute",
  "details": {
    "steps": [
      "title": "Step 1",
      "text": "step1.md",
      "courseData": "wget -q -O - https://downloads.yugabyte.com/get_clients.sh | sh",
      "code": "export PATH=$PATH:yugabyte-2.1.1.0/bin"
    ]
  },
  "environment": {
    "hideintro": true,
    "hidefinish": true,
    "uilayout": "terminal"
  },
  "backend": {
    "imageid": "ubuntu"
  }
}
